server.py
qinglong_mcp_server-0.1.5.dist-info/METADATA
qinglong_mcp_server-0.1.5.dist-info/WHEEL
qinglong_mcp_server-0.1.5.dist-info/entry_points.txt
qinglong_mcp_server-0.1.5.dist-info/licenses/LICENSE
qinglong_mcp_server-0.1.5.dist-info/RECORD
