Metadata-Version: 2.4
Name: qinglong-mcp-server
Version: 0.1.5
Summary: MCP server for Qinglong Panel task management
Author-email: Pholex <pholex@gmail.com>
License: Apache-2.0
License-File: LICENSE
Keywords: automation,mcp,qinglong
Classifier: Development Status :: 3 - Alpha
Classifier: Intended Audience :: Developers
Classifier: Programming Language :: Python :: 3
Classifier: Programming Language :: Python :: 3.8
Classifier: Programming Language :: Python :: 3.9
Classifier: Programming Language :: Python :: 3.10
Classifier: Programming Language :: Python :: 3.11
Classifier: Programming Language :: Python :: 3.12
Requires-Python: >=3.8
Requires-Dist: python-dotenv
Requires-Dist: requests
